{
  "swOBl3vq": {
    "status": "correct",
    "incorrect": 0
  },
  "m0fr8Uar": {
    "status": "correct",
    "incorrect": 0
  },
  "ys7zg7XA": {
    "status": "correct",
    "incorrect": 4
  },
  "zEbG691D": {
    "status": "correct",
    "incorrect": 2
  },
  "UlUvRTeZ": {
    "status": "correct",
    "incorrect": 7
  },
  "KowXEjGS": {
    "status": "correct",
    "incorrect": 0
  },
  "6Cnd5dzE": {
    "status": "correct",
    "incorrect": 0
  },
  "BBEpJHim": {
    "status": "correct",
    "incorrect": 2
  },
  "zCJG691D": {
    "status": "correct",
    "incorrect": 0
  },
  "UsvRTeZO": {
    "status": "correct",
    "incorrect": 0
  },
  "Ca5fVTmL": {
    "status": "correct",
    "incorrect": 0
  },
  "a7xstzDO": {
    "status": "correct",
    "incorrect": 0
  },
  "YLdhZAop": {
    "status": "correct",
    "incorrect": 0
  },
  "kZtS2WKJ": {
    "status": "correct",
    "incorrect": 0
  },
  "YtJhZAop": {
    "status": "correct",
    "incorrect": 0
  },
  "o0tmNtwx": {
    "status": "correct",
    "incorrect": 0
  },
  "4TE9OF2B": {
    "status": "correct",
    "incorrect": 0
  },
  "ADITwX1Q": {
    "status": "correct",
    "incorrect": 1
  },
  "Xe7kPIap": {
    "status": "correct",
    "incorrect": 0
  },
  "HAg44RZL": {
    "status": "correct",
    "incorrect": 0
  },
  "RPMAJFgi": {
    "status": "correct",
    "incorrect": 0
  },
  "MVLxAs7n": {
    "status": "correct",
    "incorrect": 0
  },
  "p8D2nNtD": {
    "status": "correct",
    "incorrect": 3
  },
  "RkTAJFgi": {
    "status": "correct",
    "incorrect": 0
  },
  "DnOPz728": {
    "status": "correct",
    "incorrect": 0
  },
  "cSyHRhJe": {
    "status": "correct",
    "incorrect": 1
  },
  "KpIXEjGS": {
    "status": "correct",
    "incorrect": 0
  },
  "CI1fVTmL": {
    "status": "correct",
    "incorrect": 6
  },
  "TjvKhwRH": {
    "status": "correct",
    "incorrect": 0
  },
  "sQlBl3vq": {
    "status": "correct",
    "incorrect": 4
  },
  "YvzhZAop": {
    "status": "correct",
    "incorrect": 0
  },
  "5EtuzMeL": {
    "status": "correct",
    "incorrect": 0
  },
  "xo5D8t6h": {
    "status": "correct",
    "incorrect": 0
  },
  "ghc6lhr6": {
    "status": "correct",
    "incorrect": 0
  },
  "KZ7XEjGS": {
    "status": "correct",
    "incorrect": 0
  },
  "zt5G691D": {
    "status": "correct",
    "incorrect": 5
  },
  "MotxAs7n": {
    "status": "correct",
    "incorrect": 0
  },
  "ckFHRhJe": {
    "status": "correct",
    "incorrect": 0
  },
  "bYF5uOJW": {
    "status": "correct",
    "incorrect": 0
  },
  "9SSWHnxJ": {
    "status": "correct",
    "incorrect": 0
  },
  "TSvKhwRH": {
    "status": "correct",
    "incorrect": 0
  },
  "sqHBl3vq": {
    "status": "correct",
    "incorrect": 0
  },
  "O2YiZO0v": {
    "status": "correct",
    "incorrect": 0
  },
  "mdar8Uar": {
    "status": "correct",
    "incorrect": 0
  },
  "RkaAJFgi": {
    "status": "correct",
    "incorrect": 0
  },
  "baG5uOJW": {
    "status": "correct",
    "incorrect": 0
  },
  "L4xqNrv1": {
    "status": "correct",
    "incorrect": 0
  },
  "1wsaRpKD": {
    "status": "correct",
    "incorrect": 0
  },
  "WiTlljce": {
    "status": "correct",
    "incorrect": 0
  },
  "mGtr8Uar": {
    "status": "correct",
    "incorrect": 0
  },
  "D0iPz728": {
    "status": "correct",
    "incorrect": 1
  },
  "JpgoAEXN": {
    "status": "correct",
    "incorrect": 0
  },
  "q4kUKLri": {
    "status": "correct",
    "incorrect": 0
  },
  "7UlIxIpP": {
    "status": "correct",
    "incorrect": 1
  },
  "EqZtl1dT": {
    "status": "correct",
    "incorrect": 0
  },
  "PV7e2esI": {
    "status": "correct",
    "incorrect": 0
  },
  "9TOWHnxJ": {
    "status": "correct",
    "incorrect": 0
  },
  "GEFbeioV": {
    "status": "correct",
    "incorrect": 1
  },
  "EQxtl1dT": {
    "status": "correct",
    "incorrect": 0
  },
  "IvFLNP39": {
    "status": "correct",
    "incorrect": 0
  },
  "KeQXEjGS": {
    "status": "correct",
    "incorrect": 0
  },
  "gFt6lhr6": {
    "status": "correct",
    "incorrect": 0
  },
  "FbXyul5g": {
    "status": "correct",
    "incorrect": 3
  },
  "zY6G691D": {
    "status": "correct",
    "incorrect": 1
  },
  "9kkWHnxJ": {
    "status": "correct",
    "incorrect": 0
  },
  "qOpUKLri": {
    "status": "correct",
    "incorrect": 3
  },
  "p0e2nNtD": {
    "status": "correct",
    "incorrect": 0
  },
  "BvqEpJHi": {
    "status": "correct",
    "incorrect": 0
  },
  "AkhTwX1Q": {
    "status": "correct",
    "incorrect": 0
  },
  "TPWKhwRH": {
    "status": "correct",
    "incorrect": 0
  },
  "RjXAJFgi": {
    "status": "correct",
    "incorrect": 0
  },
  "Prte2esI": {
    "status": "correct",
    "incorrect": 0
  },
  "KmGXEjGS": {
    "status": "correct",
    "incorrect": 0
  },
  "cWVHRhJe": {
    "status": "correct",
    "incorrect": 0
  },
  "OA2iZO0v": {
    "status": "correct",
    "incorrect": 2
  },
  "xJsD8t6h": {
    "status": "correct",
    "incorrect": 0
  },
  "YBnhZAop": {
    "status": "correct",
    "incorrect": 0
  },
  "WTklljce": {
    "status": "correct",
    "incorrect": 0
  },
  "z1FG691D": {
    "status": "correct",
    "incorrect": 0
  },
  "oyvmNtwx": {
    "status": "correct",
    "incorrect": 1
  },
  "HjG44RZL": {
    "status": "correct",
    "incorrect": 2
  },
  "5t7uzMeL": {
    "status": "correct",
    "incorrect": 2
  },
  "WRKlljce": {
    "status": "correct",
    "incorrect": 0
  },
  "IH5LNP39": {
    "status": "correct",
    "incorrect": 0
  },
  "j2WZrexE": {
    "status": "correct",
    "incorrect": 0
  },
  "5BEuzMeL": {
    "status": "correct",
    "incorrect": 0
  },
  "CzfVTmLk": {
    "status": "correct",
    "incorrect": 7
  },
  "gy76lhr6": {
    "status": "correct",
    "incorrect": 2
  },
  "TD4KhwRH": {
    "status": "correct",
    "incorrect": 5
  },
  "ermoQPLb": {
    "status": "correct",
    "incorrect": 2
  },
  "m61r8Uar": {
    "status": "correct",
    "incorrect": 0
  },
  "ASMTwX1Q": {
    "status": "correct",
    "incorrect": 0
  },
  "c9rHRhJe": {
    "status": "correct",
    "incorrect": 0
  },
  "fBtYBRMr": {
    "status": "correct",
    "incorrect": 0
  },
  "LWPqNrv1": {
    "status": "correct",
    "incorrect": 0
  },
  "xebD8t6h": {
    "status": "correct",
    "incorrect": 0
  },
  "GtybeioV": {
    "status": "correct",
    "incorrect": 0
  },
  "cO8HRhJe": {
    "status": "correct",
    "incorrect": 2
  },
  "L9DqNrv1": {
    "status": "correct",
    "incorrect": 0
  },
  "uBVC56DT": {
    "status": "correct",
    "incorrect": 0
  },
  "TxHKhwRH": {
    "status": "correct",
    "incorrect": 3
  },
  "cK6HRhJe": {
    "status": "correct",
    "incorrect": 0
  },
  "7ljIxIpP": {
    "status": "correct",
    "incorrect": 0
  },
  "MrIxAs7n": {
    "status": "correct",
    "incorrect": 4
  },
  "dfGF4LbF": {
    "status": "correct",
    "incorrect": 0
  },
  "7wAIxIpP": {
    "status": "correct",
    "incorrect": 1
  },
  "6ed5dzET": {
    "status": "correct",
    "incorrect": 0
  },
  "TSUKhwRH": {
    "status": "correct",
    "incorrect": 4
  },
  "Mm7xAs7n": {
    "status": "correct",
    "incorrect": 0
  },
  "lZoOiBju": {
    "status": "correct",
    "incorrect": 0
  },
  "JY3goAEX": {
    "status": "correct",
    "incorrect": 0
  },
  "RX1AJFgi": {
    "status": "correct",
    "incorrect": 0
  },
  "ut8C56DT": {
    "status": "correct",
    "incorrect": 0
  },
  "fIqYBRMr": {
    "status": "correct",
    "incorrect": 0
  },
  "1IuaRpKD": {
    "status": "correct",
    "incorrect": 0
  },
  "FsDyul5g": {
    "status": "correct",
    "incorrect": 0
  },
  "x8hD8t6h": {
    "status": "correct",
    "incorrect": 0
  },
  "2mbMJHkc": {
    "status": "correct",
    "incorrect": 0
  },
  "WA5lljce": {
    "status": "correct",
    "incorrect": 0
  },
  "y1Ezg7XA": {
    "status": "correct",
    "incorrect": 0
  },
  "zu0G691D": {
    "status": "correct",
    "incorrect": 0
  },
  "stNBl3vq": {
    "status": "correct",
    "incorrect": 0
  },
  "ogImNtwx": {
    "status": "correct",
    "incorrect": 0
  },
  "4Rs9OF2B": {
    "status": "correct",
    "incorrect": 0
  },
  "LvSqNrv1": {
    "status": "correct",
    "incorrect": 0
  },
  "fvQYBRMr": {
    "status": "correct",
    "incorrect": 0
  },
  "mzEr8Uar": {
    "status": "correct",
    "incorrect": 2
  },
  "M8UxAs7n": {
    "status": "correct",
    "incorrect": 4
  },
  "koQS2WKJ": {
    "status": "correct",
    "incorrect": 0
  },
  "aLPstzDO": {
    "status": "correct",
    "incorrect": 0
  },
  "9AlWHnxJ": {
    "status": "correct",
    "incorrect": 0
  },
  "HRJ44RZL": {
    "status": "correct",
    "incorrect": 0
  },
  "JzDgoAEX": {
    "status": "correct",
    "incorrect": 1
  },
  "q9SUKLri": {
    "status": "correct",
    "incorrect": 0
  },
  "fqvYBRMr": {
    "status": "correct",
    "incorrect": 0
  },
  "uYPC56DT": {
    "status": "correct",
    "incorrect": 0
  },
  "XMskPIap": {
    "status": "correct",
    "incorrect": 0
  },
  "qWjUKLri": {
    "status": "correct",
    "incorrect": 0
  },
  "F1Myul5g": {
    "status": "correct",
    "incorrect": 0
  },
  "aqestzDO": {
    "status": "correct",
    "incorrect": 0
  },
  "5ILuzMeL": {
    "status": "correct",
    "incorrect": 1
  },
  "sHRBl3vq": {
    "status": "correct",
    "incorrect": 1
  },
  "yC1zg7XA": {
    "status": "correct",
    "incorrect": 0
  },
  "7QRIxIpP": {
    "status": "correct",
    "incorrect": 0
  },
  "bsb5uOJW": {
    "status": "correct",
    "incorrect": 0
  },
  "p3x2nNtD": {
    "status": "correct",
    "incorrect": 0
  },
  "tQe7ji9S": {
    "status": "correct",
    "incorrect": 0
  },
  "AZDTwX1Q": {
    "status": "correct",
    "incorrect": 1
  },
  "PmEe2esI": {
    "status": "correct",
    "incorrect": 0
  },
  "cinHRhJe": {
    "status": "correct",
    "incorrect": 0
  },
  "hv41SWQP": {
    "status": "correct",
    "incorrect": 2
  },
  "gbq6lhr6": {
    "status": "correct",
    "incorrect": 1
  },
  "UwEvRTeZ": {
    "status": "correct",
    "incorrect": 0
  },
  "E9mtl1dT": {
    "status": "correct",
    "incorrect": 0
  },
  "9kAWHnxJ": {
    "status": "correct",
    "incorrect": 0
  },
  "KS3XEjGS": {
    "status": "correct",
    "incorrect": 1
  },
  "bEu5uOJW": {
    "status": "correct",
    "incorrect": 0
  },
  "eyFoQPLb": {
    "status": "correct",
    "incorrect": 0
  },
  "TMHKhwRH": {
    "status": "correct",
    "incorrect": 11
  },
  "RMZAJFgi": {
    "status": "correct",
    "incorrect": 0
  },
  "KDdXEjGS": {
    "status": "correct",
    "incorrect": 0
  },
  "C7hfVTmL": {
    "status": "correct",
    "incorrect": 0
  },
  "So2j2oe3": {
    "status": "correct",
    "incorrect": 5
  },
  "BULEpJHi": {
    "status": "correct",
    "incorrect": 0
  },
  "JyxgoAEX": {
    "status": "correct",
    "incorrect": 0
  },
  "yYszg7XA": {
    "status": "correct",
    "incorrect": 0
  },
  "D3WPz728": {
    "status": "correct",
    "incorrect": 0
  },
  "lXxOiBju": {
    "status": "correct",
    "incorrect": 0
  },
  "7WSIxIpP": {
    "status": "correct",
    "incorrect": 0
  },
  "JumgoAEX": {
    "status": "correct",
    "incorrect": 0
  },
  "XPtkPIap": {
    "status": "correct",
    "incorrect": 5
  },
  "9KKWHnxJ": {
    "status": "correct",
    "incorrect": 0
  },
  "I6LNP392": {
    "status": "correct",
    "incorrect": 0
  },
  "Ys8hZAop": {
    "status": "correct",
    "incorrect": 1
  },
  "iZFRTMow": {
    "status": "correct",
    "incorrect": 0
  },
  "AxmTwX1Q": {
    "status": "correct",
    "incorrect": 2
  },
  "ybfzg7XA": {
    "status": "correct",
    "incorrect": 1
  },
  "K2JXEjGS": {
    "status": "correct",
    "incorrect": 0
  },
  "5h1uzMeL": {
    "status": "correct",
    "incorrect": 0
  },
  "duyF4LbF": {
    "status": "correct",
    "incorrect": 7
  },
  "GYnbeioV": {
    "status": "correct",
    "incorrect": 7
  },
  "s7QBl3vq": {
    "status": "correct",
    "incorrect": 0
  },
  "atMstzDO": {
    "status": "correct",
    "incorrect": 0
  },
  "e83oQPLb": {
    "status": "correct",
    "incorrect": 0
  },
  "z5nG691D": {
    "status": "correct",
    "incorrect": 1
  },
  "ZmApgd2S": {
    "status": "correct",
    "incorrect": 0
  },
  "9ppWHnxJ": {
    "status": "correct",
    "incorrect": 0
  },
  "WAXlljce": {
    "status": "correct",
    "incorrect": 0
  },
  "OS5iZO0v": {
    "status": "correct",
    "incorrect": 0
  },
  "OkbiZO0v": {
    "status": "correct",
    "incorrect": 0
  },
  "sIwBl3vq": {
    "status": "correct",
    "incorrect": 0
  },
  "Zeipgd2S": {
    "status": "correct",
    "incorrect": 1
  },
  "79kIxIpP": {
    "status": "correct",
    "incorrect": 0
  },
  "RDqAJFgi": {
    "status": "correct",
    "incorrect": 0
  },
  "4SL9OF2B": {
    "status": "correct",
    "incorrect": 0
  },
  "UWqvRTeZ": {
    "status": "correct",
    "incorrect": 0
  },
  "Kx6XEjGS": {
    "status": "correct",
    "incorrect": 4
  },
  "LwpqNrv1": {
    "status": "correct",
    "incorrect": 0
  },
  "RiAJFgie": {
    "status": "correct",
    "incorrect": 0
  },
  "yhBzg7XA": {
    "status": "correct",
    "incorrect": 0
  },
  "1EGaRpKD": {
    "status": "correct",
    "incorrect": 0
  },
  "gCN6lhr6": {
    "status": "correct",
    "incorrect": 0
  },
  "fLUYBRMr": {
    "status": "correct",
    "incorrect": 0
  },
  "Sepj2oe3": {
    "status": "correct",
    "incorrect": 6
  },
  "653d5dzE": {
    "status": "correct",
    "incorrect": 0
  },
  "4O19OF2B": {
    "status": "correct",
    "incorrect": 5
  },
  "yuhzg7XA": {
    "status": "correct",
    "incorrect": 0
  },
  "OZCiZO0v": {
    "status": "correct",
    "incorrect": 1
  },
  "pPS2nNtD": {
    "status": "correct",
    "incorrect": 1
  },
  "5asuzMeL": {
    "status": "correct",
    "incorrect": 0
  },
  "tvD7ji9S": {
    "status": "correct",
    "incorrect": 0
  },
  "pmp2nNtD": {
    "status": "correct",
    "incorrect": 0
  },
  "M0NxAs7n": {
    "status": "correct",
    "incorrect": 0
  },
  "oFUmNtwx": {
    "status": "correct",
    "incorrect": 0
  },
  "I9CLNP39": {
    "status": "correct",
    "incorrect": 0
  },
  "mnCr8Uar": {
    "status": "correct",
    "incorrect": 0
  },
  "odqmNtwx": {
    "status": "correct",
    "incorrect": 0
  },
  "iD5RTMow": {
    "status": "correct",
    "incorrect": 0
  },
  "jmKZrexE": {
    "status": "correct",
    "incorrect": 2
  },
  "AXpTwX1Q": {
    "status": "correct",
    "incorrect": 0
  },
  "XpakPIap": {
    "status": "correct",
    "incorrect": 1
  },
  "SMkj2oe3": {
    "status": "correct",
    "incorrect": 0
  },
  "ixJRTMow": {
    "status": "correct",
    "incorrect": 1
  },
  "EIStl1dT": {
    "status": "correct",
    "incorrect": 0
  },
  "ikmRTMow": {
    "status": "correct",
    "incorrect": 2
  },
  "iK0RTMow": {
    "status": "correct",
    "incorrect": 0
  },
  "TpQKhwRH": {
    "status": "correct",
    "incorrect": 1
  },
  "X2akPIap": {
    "status": "correct",
    "incorrect": 0
  },
  "GBdbeioV": {
    "status": "correct",
    "incorrect": 0
  },
  "P8Le2esI": {
    "status": "correct",
    "incorrect": 0
  },
  "d1uF4LbF": {
    "status": "correct",
    "incorrect": 0
  },
  "avmstzDO": {
    "status": "correct",
    "incorrect": 1
  },
  "KxUXEjGS": {
    "status": "correct",
    "incorrect": 1
  },
  "LNjqNrv1": {
    "status": "correct",
    "incorrect": 0
  },
  "Wj2lljce": {
    "status": "correct",
    "incorrect": 0
  },
  "APVTwX1Q": {
    "status": "correct",
    "incorrect": 1
  },
  "sU4Bl3vq": {
    "status": "correct",
    "incorrect": 4
  },
  "GrbeioVN": {
    "status": "correct",
    "incorrect": 0
  },
  "F5kyul5g": {
    "status": "correct",
    "incorrect": 0
  },
  "Gs6beioV": {
    "status": "correct",
    "incorrect": 0
  },
  "TP9KhwRH": {
    "status": "correct",
    "incorrect": 0
  },
  "TelKhwRH": {
    "status": "correct",
    "incorrect": 0
  },
  "kxqS2WKJ": {
    "status": "correct",
    "incorrect": 0
  },
  "LimqNrv1": {
    "status": "correct",
    "incorrect": 0
  },
  "usrC56DT": {
    "status": "correct",
    "incorrect": 0
  },
  "IUdLNP39": {
    "status": "correct",
    "incorrect": 1
  },
  "TkqKhwRH": {
    "status": "correct",
    "incorrect": 0
  },
  "FCjyul5g": {
    "status": "correct",
    "incorrect": 0
  },
  "eJ0oQPLb": {
    "status": "correct",
    "incorrect": 0
  },
  "51auzMeL": {
    "status": "correct",
    "incorrect": 0
  },
  "XDEkPIap": {
    "status": "correct",
    "incorrect": 0
  },
  "yELzg7XA": {
    "status": "correct",
    "incorrect": 0
  },
  "JGPgoAEX": {
    "status": "correct",
    "incorrect": 6
  },
  "iS6RTMow": {
    "status": "correct",
    "incorrect": 6
  },
  "AjxTwX1Q": {
    "status": "correct",
    "incorrect": 0
  },
  "GC3beioV": {
    "status": "correct",
    "incorrect": 1
  },
  "7vOIxIpP": {
    "status": "correct",
    "incorrect": 0
  },
  "SxSj2oe3": {
    "status": "correct",
    "incorrect": 3
  },
  "XxEkPIap": {
    "status": "correct",
    "incorrect": 8
  },
  "KMgXEjGS": {
    "status": "correct",
    "incorrect": 1
  },
  "XYkPIapg": {
    "status": "correct",
    "incorrect": 22
  },
  "5LquzMeL": {
    "status": "correct",
    "incorrect": 0
  },
  "tqM7ji9S": {
    "status": "correct",
    "incorrect": 0
  },
  "qwTUKLri": {
    "status": "correct",
    "incorrect": 0
  },
  "dCzF4LbF": {
    "status": "correct",
    "incorrect": 0
  },
  "OjoiZO0v": {
    "status": "correct",
    "incorrect": 0
  },
  "OMhiZO0v": {
    "status": "correct",
    "incorrect": 0
  },
  "yBIzg7XA": {
    "status": "correct",
    "incorrect": 0
  },
  "9AAWHnxJ": {
    "status": "correct",
    "incorrect": 0
  },
  "XjYkPIap": {
    "status": "correct",
    "incorrect": 0
  },
  "S3Pj2oe3": {
    "status": "correct",
    "incorrect": 7
  },
  "KBXEjGSH": {
    "status": "correct",
    "incorrect": 1
  },
  "E4otl1dT": {
    "status": "correct",
    "incorrect": 0
  },
  "ELjtl1dT": {
    "status": "correct",
    "incorrect": 0
  },
  "pej2nNtD": {
    "status": "correct",
    "incorrect": 0
  },
  "mJYr8Uar": {
    "status": "correct",
    "incorrect": 4
  },
  "9i9WHnxJ": {
    "status": "correct",
    "incorrect": 1
  },
  "IWfLNP39": {
    "status": "correct",
    "incorrect": 9
  },
  "6Grd5dzE": {
    "status": "correct",
    "incorrect": 0
  },
  "1BzaRpKD": {
    "status": "correct",
    "incorrect": 0
  },
  "qlZUKLri": {
    "status": "correct",
    "incorrect": 0
  },
  "RSsAJFgi": {
    "status": "correct",
    "incorrect": 0
  },
  "9XXWHnxJ": {
    "status": "correct",
    "incorrect": 0
  },
  "bC65uOJW": {
    "status": "correct",
    "incorrect": 0
  },
  "Hi044RZL": {
    "status": "correct",
    "incorrect": 6
  },
  "C1bfVTmL": {
    "status": "correct",
    "incorrect": 1
  },
  "RKhAJFgi": {
    "status": "correct",
    "incorrect": 0
  },
  "tNP7ji9S": {
    "status": "correct",
    "incorrect": 0
  },
  "HKd44RZL": {
    "status": "correct",
    "incorrect": 0
  }
}